odoo9_addon_report_qweb_element_page_visibility-9.0.1.0.0.99.dev3-py2.7-nspkg.pth
odoo9_addon_report_qweb_element_page_visibility-9.0.1.0.0.99.dev3.dist-info/DESCRIPTION.rst
odoo9_addon_report_qweb_element_page_visibility-9.0.1.0.0.99.dev3.dist-info/METADATA
odoo9_addon_report_qweb_element_page_visibility-9.0.1.0.0.99.dev3.dist-info/RECORD
odoo9_addon_report_qweb_element_page_visibility-9.0.1.0.0.99.dev3.dist-info/WHEEL
odoo9_addon_report_qweb_element_page_visibility-9.0.1.0.0.99.dev3.dist-info/metadata.json
odoo9_addon_report_qweb_element_page_visibility-9.0.1.0.0.99.dev3.dist-info/namespace_packages.txt
odoo9_addon_report_qweb_element_page_visibility-9.0.1.0.0.99.dev3.dist-info/top_level.txt
odoo_addons/report_qweb_element_page_visibility/README.rst
odoo_addons/report_qweb_element_page_visibility/__init__.py
odoo_addons/report_qweb_element_page_visibility/__openerp__.py
odoo_addons/report_qweb_element_page_visibility/i18n/report_qweb_element_page_visibility.pot
odoo_addons/report_qweb_element_page_visibility/static/description/icon.png
odoo_addons/report_qweb_element_page_visibility/views/layouts.xml
