Metadata-Version: 2.0
Name: odoo9-addon-report-qweb-element-page-visibility
Version: 9.0.1.0.0.99.dev3
Summary: Report Qweb Element Page Visibility
Home-page: https://odoo-community.org/
Author: Agile Business Group, Odoo Community Association (OCA)
Author-email: support@odoo-community.org
License: AGPL-3
Platform: UNKNOWN
Classifier: Programming Language :: Python
Classifier: Framework :: Odoo
Classifier: License :: OSI Approved :: GNU Affero General Public License v3
Requires-Python: ~=2.7
Requires-Dist: odoo (<9.1a,>=9.0a)
